lowearthorbit/__init__.py
lowearthorbit/delete.py
lowearthorbit/deploy.py
lowearthorbit/leo.py
lowearthorbit/plan.py
lowearthorbit/upload.py
lowearthorbit/validate.py
lowearthorbit/resources/__init__.py
lowearthorbit/resources/capabilities.py
lowearthorbit/resources/changes.py
lowearthorbit/resources/create.py
lowearthorbit/resources/parameters.py
lowearthorbit/resources/update.py
lowearthorbit/tests/__init__.py
lowearthorbit/tests/test_functional.py
lowearthorbit/tests/test_resources.py
LowEarthOrbit-0.7.7.dist-info/LICENSE.txt
LowEarthOrbit-0.7.7.dist-info/METADATA
LowEarthOrbit-0.7.7.dist-info/WHEEL
LowEarthOrbit-0.7.7.dist-info/entry_points.txt
LowEarthOrbit-0.7.7.dist-info/top_level.txt
LowEarthOrbit-0.7.7.dist-info/RECORD
