Metadata-Version: 2.1
Name: LowEarthOrbit
Version: 0.7.7
Summary: A better way to deploy AWS CloudFormation
Home-page: UNKNOWN
Author: Nicholas Christian
Author-email: ndchristian@gmail.com
License: LICENSE.txt
Platform: UNKNOWN
Requires-Dist: click
Requires-Dist: botocore
Requires-Dist: boto3
